{ "compressionlevel":-1,
 "editorsettings":
    {
     "export":
        {
         "target":"."
        }
    },
 "height":27,
 "infinite":false,
 "layers":[
        {
         "compression":"zstd",
         "data":"KLUv\/WCkA30DAIgAAAEEBAQABAQABAQABAQEATqgkH0gAxIaFwMPHoXINdmfcMNzeQYPWxPH6IzkXMhkFnZt\/cCfxnH8Bn4XeAYDrdfNTRrIHPjzV89bOe1M6m6hE\/WsSpE0NGNGEyYGwiWTUsD77qX+lIp5jGSYAg==",
         "encoding":"base64",
         "height":27,
         "id":1,
         "name":"Ground",
         "opacity":1,
         "type":"tilelayer",
         "visible":true,
         "width":11,
         "x":0,
         "y":0
        }, 
        {
         "compression":"zstd",
         "data":"KLUv\/WCkA60AACgAAAcABwQAREBJe46gwBpQ4ZsCLA==",
         "encoding":"base64",
         "height":27,
         "id":4,
         "name":"Item",
         "opacity":1,
         "type":"tilelayer",
         "visible":true,
         "width":11,
         "x":0,
         "y":0
        }, 
        {
         "compression":"zstd",
         "data":"KLUv\/WCkA20AACAAAAIAAgAHEt7iB1g=",
         "encoding":"base64",
         "height":27,
         "id":2,
         "name":"Player",
         "opacity":1,
         "type":"tilelayer",
         "visible":true,
         "width":11,
         "x":0,
         "y":0
        }, 
        {
         "compression":"zstd",
         "data":"KLUv\/WCkA20AACAAAAMAAgBfgB9PAlg=",
         "encoding":"base64",
         "height":27,
         "id":3,
         "name":"Candle",
         "opacity":1,
         "type":"tilelayer",
         "visible":true,
         "width":11,
         "x":0,
         "y":0
        }, 
        {
         "compression":"zstd",
         "data":"KLUv\/WCkA1UBAEAAABIAEhISAAuAIO8BbWlSQxwV4JsfBLXB9KpT7pAGQnpmcCtAvROwAQ==",
         "encoding":"base64",
         "height":27,
         "id":5,
         "name":"Switch",
         "opacity":1,
         "type":"tilelayer",
         "visible":true,
         "width":11,
         "x":0,
         "y":0
        }],
 "nextlayerid":6,
 "nextobjectid":1,
 "orientation":"orthogonal",
 "renderorder":"right-down",
 "tiledversion":"1.4.1",
 "tileheight":32,
 "tilesets":[
        {
         "firstgid":1,
         "source":"tile.tsx"
        }],
 "tilewidth":32,
 "type":"map",
 "version":1.4,
 "width":11
}